litter/__init__.py
litter/main.py
litter/tests/__init__.py
litter/tests/upload_test.py
litter/uploader/__init__.py
litter/uploader/base.py
litter/uploader/catbox.py
litter/uploader/litterbox.py
pylitter-1.1.1.dist-info/LICENSE
pylitter-1.1.1.dist-info/METADATA
pylitter-1.1.1.dist-info/WHEEL
pylitter-1.1.1.dist-info/entry_points.txt
pylitter-1.1.1.dist-info/top_level.txt
pylitter-1.1.1.dist-info/RECORD
