Metadata-Version: 2.1
Name: pylitter
Version: 1.1.1
Summary: CLI tool to upload file to litterbox/catbox
Home-page: https://github.com/moiSentineL/litter
Author: moisentinel, yukinotenshi
Author-email: nibir@nibirsan.org, gabriel.bentara@gmail.com
License: MIT
Keywords: direct upload cli
Classifier: Development Status :: 5 - Production/Stable
Classifier: License :: OSI Approved :: MIT License
Classifier: Natural Language :: English
Classifier: Operating System :: OS Independent
Classifier: Programming Language :: Python :: 3
License-File: LICENSE
Requires-Dist: requests
Requires-Dist: requests-toolbelt
Requires-Dist: click
